MANIFEST.in
setup.py
aruco/LICENSE
aruco/README.md
aruco/__init__.py
aruco/arucoPYTHON_wrap.cxx
aruco/arucoPYTHON_wrap.h
aruco/pyaruco.py
aruco.egg-info/PKG-INFO
aruco.egg-info/SOURCES.txt
aruco.egg-info/dependency_links.txt
aruco.egg-info/requires.txt
aruco.egg-info/top_level.txt
aruco/include/aruco.h
aruco/include/aruco_cvversioning.h
aruco/include/aruco_export.h
aruco/include/cameraparameters.h
aruco/include/cvdrawingutils.h
aruco/include/debug.h
aruco/include/dictionary.h
aruco/include/dictionary_based.h
aruco/include/fractaldetector.h
aruco/include/ippe.h
aruco/include/levmarq.h
aruco/include/marker.h
aruco/include/markerdetector.h
aruco/include/markerdetector_impl.h
aruco/include/markerlabeler.h
aruco/include/markermap.h
aruco/include/picoflann.h
aruco/include/posetracker.h
aruco/include/timers.h
aruco/include/dcf/dcf_utils.h
aruco/include/dcf/dcfmarkermaptracker.h
aruco/include/dcf/dcfmarkertracker.h
aruco/include/dcf/trackerimpl.h
aruco/include/fractallabelers/fractallabeler.h
aruco/include/fractallabelers/fractalmarker.h
aruco/include/fractallabelers/fractalmarkerset.h
aruco/include/fractallabelers/fractalposetracker.h