Metadata-Version: 2.1
Name: aruco
Version: 3.1.12.0
Summary: ArUco Python wrappers
Home-page: https://github.com/fehlfarbe/python-aruco
Author: ArUco: Rafael Muñoz Salinas, Python wrappers: Marcus Degenkolbe
Author-email: marcus@degenkolbe.eu
License: Copyright 2017 Rafael Muñoz Salinas. All rights reserved.
Keywords: aruco wrapper
Platform: UNKNOWN
